setup.py
easyredditbot/__init__.py
easyredditbot/api.py
easyredditbot/version.py
easyredditbot.egg-info/PKG-INFO
easyredditbot.egg-info/SOURCES.txt
easyredditbot.egg-info/dependency_links.txt
easyredditbot.egg-info/not-zip-safe
easyredditbot.egg-info/requires.txt
easyredditbot.egg-info/top_level.txt