Metadata-Version: 1.1
Name: easyredditbot
Version: 0.1.0
Summary: Create a reddit bot as quickly as possible
Home-page: http://github.com/teaearlgraycold/easyredditbot
Author: teaearlgraycold
Author-email: UNKNOWN
License: GPLv3
Platform: UNKNOWN
Classifier: Development Status :: 3 - Alpha
Classifier: Environment :: Console
Classifier: Intended Audience :: Developers
Classifier: License :: OSI Approved :: GNU General Public License (GPL)
Classifier: Programming Language :: Python :: 2.7
Classifier: Programming Language :: Python :: 3.6
Classifier: Programming Language :: Python :: Implementation :: CPython
Classifier: Topic :: Utilities
